{
  "date": "20260723",
  "updated_at": "2026-07-23 19:29:41",
  "market_data": {
    "S&P 500": {
      "current": 7398.51,
      "change_pct": -1.34
    },
    "NASDAQ": {
      "current": 25091.27,
      "change_pct": -2.33
    },
    "다우존스": {
      "current": 51699.61,
      "change_pct": -0.99
    },
    "VIX 공포지수": {
      "current": 19.51,
      "change_pct": 17.25
    },
    "달러인덱스": {
      "current": 101.46,
      "change_pct": 0.32
    }
  },
  "analysis": {
    "market_summary": "미국 증시 전반적 분위기는 악화되는 모습을 보이는데, 주요 지수인 S&P 500, NASDAQ, 다우존스 모두 하락하였다. 특히 VIX 공포지수가 17.25% 상승한 것으로 보여 투자자들의 불안감이 높아진 것으로 보인다.",
    "kr_market_outlook": "오늘 한국 시장은 어제 하락한 종목들이 반등할 가능성이 있으나, 미국 시장의 악화된 분위기로 인해 신중한 접근이 필요할 것으로 보인다. 하락 종목이 제공되지 않았으므로, 전체적으로 한국 주식시장의 반응을 주시할 필요가 있다.",
    "buy_candidates": [],
    "risk_factors": "미국 증시의 악화된 분위기, 달러인덱스의 상승, तथ다한 투자자들의 불안감을 주의해야 한다."
  },
  "screening_date": "20260617",
  "screening_count": 0
}